Package/__init__.py
Package/topsis_package_file.py
vkhanduja-0.0.2.dist-info/LICENSE.txt
vkhanduja-0.0.2.dist-info/METADATA
vkhanduja-0.0.2.dist-info/WHEEL
vkhanduja-0.0.2.dist-info/top_level.txt
vkhanduja-0.0.2.dist-info/RECORD
