Metadata-Version: 2.1
Name: vkhanduja
Version: 0.0.2
Summary: TOPSIS for MCDM
Home-page: 
Author: Vivek Khanduja
Author-email: vkhanduja28@gmail.com
License: UNKNOWN
Platform: UNKNOWN
Classifier: Programming Language :: Python :: 3
Classifier: License :: OSI Approved :: MIT License
Classifier: Operating System :: OS Independent
Requires-Python: >=3.6
